{
  "UserEvents": {
    "35a4a73f54888938fe153e292bc5717227e7b35295fc93f5c2f5d6260dc8910a": [
      {
        "NewName": "GameScreenGum",
        "OldName": null,
        "ElementType": "Screens",
        "EventType": 0,
        "TimestampUtc": "2025-11-18T13:46:18.9153048Z"
      },
      {
        "NewName": "GameScreenGum.LabelInstance",
        "OldName": null,
        "ElementType": "Screens",
        "EventType": 5,
        "TimestampUtc": "2025-11-18T13:46:48.9941732Z"
      },
      {
        "NewName": "GameScreenGum.CurvePointEditorWindow",
        "OldName": null,
        "ElementType": "Screens",
        "EventType": 5,
        "TimestampUtc": "2025-11-18T13:46:49.0346315Z"
      },
      {
        "NewName": "GameScreenGum.StartPointText",
        "OldName": null,
        "ElementType": "Screens",
        "EventType": 5,
        "TimestampUtc": "2025-11-18T13:46:49.0732283Z"
      },
      {
        "NewName": "GameScreenGum.KeyPoint1Text",
        "OldName": null,
        "ElementType": "Screens",
        "EventType": 5,
        "TimestampUtc": "2025-11-18T13:46:49.1086984Z"
      },
      {
        "NewName": "GameScreenGum.EndPointText",
        "OldName": null,
        "ElementType": "Screens",
        "EventType": 5,
        "TimestampUtc": "2025-11-18T13:46:49.1451858Z"
      },
      {
        "NewName": "GameScreenGum.KeyPoint2Text",
        "OldName": null,
        "ElementType": "Screens",
        "EventType": 5,
        "TimestampUtc": "2025-11-18T13:46:49.1806731Z"
      },
      {
        "NewName": "GameScreenGum.StartPointXBox",
        "OldName": null,
        "ElementType": "Screens",
        "EventType": 5,
        "TimestampUtc": "2025-11-18T13:46:49.2208649Z"
      },
      {
        "NewName": "GameScreenGum.KeyPoint1XBox",
        "OldName": null,
        "ElementType": "Screens",
        "EventType": 5,
        "TimestampUtc": "2025-11-18T13:46:49.2622924Z"
      },
      {
        "NewName": "GameScreenGum.EndPointXBox",
        "OldName": null,
        "ElementType": "Screens",
        "EventType": 5,
        "TimestampUtc": "2025-11-18T13:46:49.3006073Z"
      },
      {
        "NewName": "GameScreenGum.KeyPoint2XBox",
        "OldName": null,
        "ElementType": "Screens",
        "EventType": 5,
        "TimestampUtc": "2025-11-18T13:46:49.3378473Z"
      },
      {
        "NewName": "GameScreenGum.StartPointYBox",
        "OldName": null,
        "ElementType": "Screens",
        "EventType": 5,
        "TimestampUtc": "2025-11-18T13:46:49.372569Z"
      },
      {
        "NewName": "GameScreenGum.KeyPoint1YBox",
        "OldName": null,
        "ElementType": "Screens",
        "EventType": 5,
        "TimestampUtc": "2025-11-18T13:46:49.4085099Z"
      },
      {
        "NewName": "GameScreenGum.EndPointYBox",
        "OldName": null,
        "ElementType": "Screens",
        "EventType": 5,
        "TimestampUtc": "2025-11-18T13:46:49.4450104Z"
      },
      {
        "NewName": "GameScreenGum.KeyPoint2YBox",
        "OldName": null,
        "ElementType": "Screens",
        "EventType": 5,
        "TimestampUtc": "2025-11-18T13:46:49.4808276Z"
      },
      {
        "NewName": null,
        "OldName": "GameScreenGum.Text StartPointText in GameScreenGum",
        "ElementType": "Screens",
        "EventType": 6,
        "TimestampUtc": "2025-11-18T13:50:50.4494498Z"
      },
      {
        "NewName": null,
        "OldName": "GameScreenGum.Controls/TextBox StartPointXBox in GameScreenGum",
        "ElementType": "Screens",
        "EventType": 6,
        "TimestampUtc": "2025-11-18T13:50:50.4504465Z"
      },
      {
        "NewName": null,
        "OldName": "GameScreenGum.Controls/TextBox KeyPoint2YBox in GameScreenGum",
        "ElementType": "Screens",
        "EventType": 6,
        "TimestampUtc": "2025-11-18T13:50:50.4607472Z"
      },
      {
        "NewName": null,
        "OldName": "GameScreenGum.Controls/TextBox KeyPoint2XBox in GameScreenGum",
        "ElementType": "Screens",
        "EventType": 6,
        "TimestampUtc": "2025-11-18T13:50:50.4686118Z"
      },
      {
        "NewName": null,
        "OldName": "GameScreenGum.Text KeyPoint2Text in GameScreenGum",
        "ElementType": "Screens",
        "EventType": 6,
        "TimestampUtc": "2025-11-18T13:50:50.478187Z"
      },
      {
        "NewName": null,
        "OldName": "GameScreenGum.Text KeyPoint1Text in GameScreenGum",
        "ElementType": "Screens",
        "EventType": 6,
        "TimestampUtc": "2025-11-18T13:50:50.4865576Z"
      },
      {
        "NewName": null,
        "OldName": "GameScreenGum.Controls/TextBox KeyPoint1XBox in GameScreenGum",
        "ElementType": "Screens",
        "EventType": 6,
        "TimestampUtc": "2025-11-18T14:03:06.6312234Z"
      },
      {
        "NewName": null,
        "OldName": "GameScreenGum.Controls/TextBox StartPointYBox in GameScreenGum",
        "ElementType": "Screens",
        "EventType": 6,
        "TimestampUtc": "2025-11-18T14:03:06.6327295Z"
      },
      {
        "NewName": null,
        "OldName": "GameScreenGum.Controls/TextBox KeyPoint1YBox in GameScreenGum",
        "ElementType": "Screens",
        "EventType": 6,
        "TimestampUtc": "2025-11-18T14:03:06.6442915Z"
      },
      {
        "NewName": null,
        "OldName": "GameScreenGum.Controls/TextBox EndPointYBox in GameScreenGum",
        "ElementType": "Screens",
        "EventType": 6,
        "TimestampUtc": "2025-11-18T14:03:06.652785Z"
      },
      {
        "NewName": null,
        "OldName": "GameScreenGum.Controls/TextBox EndPointXBox in GameScreenGum",
        "ElementType": "Screens",
        "EventType": 6,
        "TimestampUtc": "2025-11-18T14:03:06.6609536Z"
      },
      {
        "NewName": null,
        "OldName": "GameScreenGum.Text EndPointText in GameScreenGum",
        "ElementType": "Screens",
        "EventType": 6,
        "TimestampUtc": "2025-11-18T14:03:06.6690262Z"
      },
      {
        "NewName": null,
        "OldName": "GameScreenGum.Controls/WindowStandard CurvePointEditorWindow in GameScreenGum",
        "ElementType": "Screens",
        "EventType": 6,
        "TimestampUtc": "2025-11-18T14:09:34.3140194Z"
      },
      {
        "NewName": "GameScreenGum.ScoreLabel",
        "OldName": "GameScreenGum.LabelInstance",
        "ElementType": "Screens",
        "EventType": 7,
        "TimestampUtc": "2025-11-18T14:11:29.7571615Z"
      },
      {
        "NewName": "CurveEditorScreenGum.CheckBoxInstance",
        "OldName": null,
        "ElementType": "Screens",
        "EventType": 5,
        "TimestampUtc": "2025-11-18T14:44:35.4221586Z"
      },
      {
        "NewName": "CurveEditorScreenGum.GridBox",
        "OldName": "CurveEditorScreenGum.CheckBoxInstance",
        "ElementType": "Screens",
        "EventType": 7,
        "TimestampUtc": "2025-11-18T14:45:04.1477062Z"
      },
      {
        "NewName": "LevelEditorScreenGum",
        "OldName": null,
        "ElementType": "Screens",
        "EventType": 0,
        "TimestampUtc": "2025-11-28T10:18:03.0477504Z"
      }
    ]
  }
}